cndetect/__init__.py
cndetect/cli.py
cndetect/config.py
cndetect/core.py
cndetect/logger.py
cndetect/data/family.txt
cndetect/data/pinyin_family.txt
cndetect/data/pinyin_syllables.txt
chinese_name_detector-0.2.1.dist-info/entry_points.txt
chinese_name_detector-0.2.1.dist-info/licenses/LICENSE
chinese_name_detector-0.2.1.dist-info/WHEEL
chinese_name_detector-0.2.1.dist-info/METADATA
chinese_name_detector-0.2.1.dist-info/RECORD
