Metadata-Version: 2.4
Name: chinese-name-detector
Version: 0.2.1
Summary: A lightweight tool to detect Chinese characters and surnames.
Author-email: Chandler <275737875@qq.com>
Requires-Python: >=3.8
License-File: LICENSE
Requires-Dist: pandas
Requires-Dist: openpyxl
Requires-Dist: typer[all]
Requires-Dist: rich
Requires-Dist: pyyaml
Requires-Dist: pydantic
Requires-Dist: pydantic-settings
Requires-Dist: loguru
